hexfft/__init__.py
hexfft/array.py
hexfft/grids.py
hexfft/hexfft.py
hexfft/plot.py
hexfft/reference.py
hexfft/utils.py
hexfft-0.1.4.dist-info/LICENSE
hexfft-0.1.4.dist-info/METADATA
hexfft-0.1.4.dist-info/WHEEL
hexfft-0.1.4.dist-info/top_level.txt
hexfft-0.1.4.dist-info/RECORD
