Metadata-Version: 2.1
Name: hexfft
Version: 0.1.4
Summary: Hexagonal FFTs in Python
Author-email: Chris Langfield <christopher.langfield@gmail.com>
Keywords: hexagonal,dsp,fft
Requires-Python: >=3.8
License-File: LICENSE
